{
  "name": "K",
  "status": "M",
  "elements": [
    {
      "name": "controlId",
      "originalName": "Control Identifier",
      "sec": 1,
      "status": "M",
      "start": 1,
      "end": 1,
      "filler": " ",
      "align": "Left",
      "max": 1,
      "class": "A",
      "description": "Must always equal K"
    },
    {
      "name": "filler1",
      "originalName": "Filler",
      "sec": 2,
      "status": "M",
      "start": 2,
      "end": 2,
      "filler": " ",
      "align": "Left",
      "max": 1,
      "class": "S",
      "description": "<p>Always space.</p>"
    },
    {
      "name": "importerNumber1",
      "originalName": "Importer Number 1",
      "sec": 3,
      "status": "M",
      "start": 3,
      "end": 14,
      "filler": " ",
      "align": "Left",
      "max": 12,
      "class": "X",
      "description": "A code representing the importer/consignee."
    },
    {
      "name": "addressRequestCode1",
      "originalName": "Address Request Code 1",
      "sec": 4,
      "status": "M",
      "start": 15,
      "end": 15,
      "filler": " ",
      "align": "Left",
      "max": 12,
      "class": "X",
      "description": "The address request code."
    },
    {
      "name": "importerNumber2",
      "originalName": "Importer Number 2",
      "sec": 5,
      "status": "C",
      "start": 16,
      "end": 27,
      "filler": " ",
      "align": "Left",
      "max": 12,
      "class": "X",
      "description": "An additional code representing an importer/consignee and the address request code.<br /><br /> Space fill if not used."
    },
    {
      "name": "addressRequestCode2",
      "originalName": "Address Request Code 2",
      "sec": 6,
      "status": "C",
      "start": 28,
      "end": 28,
      "filler": " ",
      "align": "Left",
      "max": 1,
      "class": "AN",
      "description": "An additional code representing an importer/consignee and the address request code.<br /><br /> Space fill if not used."
    },
    {
      "name": "importerNumber3",
      "originalName": "Importer Number 3",
      "sec": 7,
      "status": "C",
      "start": 29,
      "end": 40,
      "filler": " ",
      "align": "Left",
      "max": 12,
      "class": "X",
      "description": "An additional code representing an importer/consignee and the address request code.<br /><br /> Space fill if not used."
    },
    {
      "name": "addressRequestCode3",
      "originalName": "Address Request Code 3",
      "sec": 8,
      "status": "C",
      "start": 41,
      "end": 41,
      "filler": " ",
      "align": "Left",
      "max": 1,
      "class": "AN",
      "description": "An additional code representing an importer/consignee and the address request code.<br /><br /> Space fill if not used."
    },
    {
      "name": "importerNumber4",
      "originalName": "Importer Number 4",
      "sec": 9,
      "status": "C",
      "start": 42,
      "end": 53,
      "filler": " ",
      "align": "Left",
      "max": 12,
      "class": "X",
      "description": "An additional code representing an importer/consignee and the address request code.<br /><br /> Space fill if not used."
    },
    {
      "name": "addressRequestCode4",
      "originalName": "Address Request Code 4",
      "sec": 10,
      "status": "C",
      "start": 54,
      "end": 54,
      "filler": " ",
      "align": "Left",
      "max": 1,
      "class": "AN",
      "description": "An additional code representing an importer/consignee and the address request code.<br /><br /> Space fill if not used."
    },
    {
      "name": "importerNumber5",
      "originalName": "Importer Number 5",
      "sec": 11,
      "status": "C",
      "start": 55,
      "end": 66,
      "filler": " ",
      "align": "Left",
      "max": 12,
      "class": "X",
      "description": "An additional code representing an importer/consignee and the address request code.<br /><br /> Space fill if not used."
    },
    {
      "name": "addressRequestCode5",
      "originalName": "Address Request Code 5",
      "sec": 12,
      "status": "C",
      "start": 67,
      "end": 67,
      "filler": " ",
      "align": "Left",
      "max": 1,
      "class": "AN",
      "description": "An additional code representing an importer/consignee and the address request code.<br /><br /> Space fill if not used."
    },
    {
      "name": "importerNumber6",
      "originalName": "Importer Number 6",
      "sec": 13,
      "status": "C",
      "start": 68,
      "end": 79,
      "filler": " ",
      "align": "Left",
      "max": 12,
      "class": "X",
      "description": "An additional code representing an importer/consignee and the address request code.<br /><br /> Space fill if not used."
    },
    {
      "name": "addressRequestCode6",
      "originalName": "Address Request Code 6",
      "sec": 14,
      "status": "C",
      "start": 80,
      "end": 80,
      "filler": " ",
      "align": "Left",
      "max": 1,
      "class": "AN",
      "description": "An additional code representing an importer/consignee and the address request code.<br /><br /> Space fill if not used."
    }
  ]
}
